{
    "version": "https://jsonfeed.org/version/1",
    "title": "Test",
    "description": "",
    "home_page_url": "https://mrflos.github.io/publii",
    "feed_url": "https://mrflos.github.io/publii/feed.json",
    "user_comment": "",
    "author": {
        "name": "mrflos"
    },
    "items": [
        {
            "id": "https://mrflos.github.io/publii/preums.html",
            "url": "https://mrflos.github.io/publii/preums.html",
            "title": "Preums!",
            "summary": "barbonhommesnaturejoliemangeryoupi ",
            "content_html": "<div class=\"gallery-wrapper\"><div class=\"gallery\"  data-is-empty=\"false\" data-columns=\"5\">\n<figure class=\"gallery__item\"><a href=\"https://mrflos.github.io/publii/media/posts/1/gallery/chihiro007.jpg\" data-size=\"1920x1038\"><img loading=\"lazy\" src=\"https://mrflos.github.io/publii/media/posts/1/gallery/chihiro007-thumbnail.jpg\" alt=\"bar\" width=\"720\" height=\"389\"></a>\n<figcaption>bar</figcaption>\n</figure>\n<figure class=\"gallery__item\"><a href=\"https://mrflos.github.io/publii/media/posts/1/gallery/chihiro014.jpg\" data-size=\"1920x1038\"><img loading=\"lazy\" src=\"https://mrflos.github.io/publii/media/posts/1/gallery/chihiro014-thumbnail.jpg\" alt=\"bonhommes\" width=\"720\" height=\"389\"></a>\n<figcaption>bonhommes</figcaption>\n</figure>\n<figure class=\"gallery__item\"><a href=\"https://mrflos.github.io/publii/media/posts/1/gallery/karigurashi001.jpg\" data-size=\"1920x1038\"><img loading=\"lazy\" src=\"https://mrflos.github.io/publii/media/posts/1/gallery/karigurashi001-thumbnail.jpg\" alt=\"nature\" width=\"720\" height=\"389\"></a>\n<figcaption>nature</figcaption>\n</figure>\n<figure class=\"gallery__item\"><a href=\"https://mrflos.github.io/publii/media/posts/1/gallery/karigurashi007.jpg\" data-size=\"1920x1038\"><img loading=\"lazy\" src=\"https://mrflos.github.io/publii/media/posts/1/gallery/karigurashi007-thumbnail.jpg\" alt=\"jolie\" width=\"720\" height=\"389\"></a>\n<figcaption>jolie</figcaption>\n</figure>\n<figure class=\"gallery__item\"><a href=\"https://mrflos.github.io/publii/media/posts/1/gallery/chihiro030.jpg\" data-size=\"1920x1038\"><img loading=\"lazy\" src=\"https://mrflos.github.io/publii/media/posts/1/gallery/chihiro030-thumbnail.jpg\" alt=\"manger\" width=\"720\" height=\"389\"></a>\n<figcaption>manger</figcaption>\n</figure>\n</div></div>\n<p>youpi </p>",
            "image": "https://mrflos.github.io/publii/media/posts/1/chihiro030.jpg",
            "author": {
                "name": "mrflos"
            },
            "tags": [
            ],
            "date_published": "2021-03-07T17:39:05+03:00",
            "date_modified": "2021-03-07T17:40:07+03:00"
        }
    ]
}
